realloc/__init__.py
realloc/accounts.py
realloc/allocator.py
realloc/models.py
realloc/portfolio.py
realloc/prices.py
realloc/selectors.py
realloc/trades.py
realloc/utils.py
realloc/cli/__init__.py
realloc/cli/partial_rebalance_main.py
realloc/cli/rebalance_csv_input.py
realloc/cli/rebalance_json_input.py
realloc/plugins/__init__.py
realloc/plugins/core/__init__.py
realloc/plugins/core/base.py
realloc/plugins/core/discovery.py
realloc/plugins/core/engine.py
realloc/plugins/exporters/__init__.py
realloc/plugins/exporters/csv_exporter.py
realloc/plugins/importers/__init__.py
realloc/plugins/importers/account/__init__.py
realloc/plugins/importers/account/account_csv.py
realloc/plugins/importers/allocation/__init__.py
realloc/plugins/importers/allocation/allocation_csv.py
realloc/plugins/importers/prices/__init__.py
realloc/plugins/importers/prices/prices_csv.py
realloc/plugins/rebalancers/__init__.py
realloc/plugins/rebalancers/default_rebalancer.py
realloc/plugins/validators/__init__.py
realloc/plugins/validators/max_position.py
realloc/plugins/validators/minimum_value.py
realloc/scripts/end_to_end_1.py
realloc-0.1.5.2.dist-info/METADATA
realloc-0.1.5.2.dist-info/WHEEL
realloc-0.1.5.2.dist-info/entry_points.txt
realloc-0.1.5.2.dist-info/top_level.txt
realloc-0.1.5.2.dist-info/RECORD
