Metadata-Version: 2.4
Name: realloc
Version: 0.1.5.2
Summary: A modular Python library for multi-account portfolio trade allocation
Author-email: Ryeland Gongora <rsgmon@gmail.com>
License-Expression: MIT
Requires-Python: >=3.8
Provides-Extra: dev
Requires-Dist: pytest; extra == "dev"
Requires-Dist: pytest-cov; extra == "dev"
Requires-Dist: black; extra == "dev"
Requires-Dist: flake8; extra == "dev"
Requires-Dist: hypothesis; extra == "dev"
